slackd/__init__.py
slackd/alert.py
slackd/functions.py
slackd/send_alert.py
slackd/utils.py
slackd-0.0.5.dist-info/LICENSE
slackd-0.0.5.dist-info/METADATA
slackd-0.0.5.dist-info/WHEEL
slackd-0.0.5.dist-info/top_level.txt
slackd-0.0.5.dist-info/RECORD
