Metadata-Version: 2.1
Name: slackd
Version: 0.0.5
Summary: SlackD package to send pretty message to slack channel
Home-page: https://github.com/pypa/sampleproject
Author-email: xgz <xiuyangguan@gmail.com>
License: UNKNOWN
Project-URL: Homepage, https://github.com/pypa/sampleproject
Project-URL: Bug Tracker, https://github.com/pypa/sampleproject/issues
Platform: UNKNOWN
Classifier: Programming Language :: Python :: 3
Classifier: License :: OSI Approved :: MIT License
Classifier: Operating System :: OS Independent
Requires-Python: >=3.8
License-File: LICENSE
